{"stats":{"minecraft:custom":{"cuffed:legcuffs_times_restrained":7,"minecraft:time_since_rest":29684,"cuffed:handcuffs_times_restrained":9,"minecraft:sprint_one_cm":273187,"minecraft:damage_taken":1780,"minecraft:walk_one_cm":305880,"minecraft:drop":23,"minecraft:inspect_hopper":1,"minecraft:damage_dealt":130,"cuffed:handcuffs_time_spent_restrained":18443,"minecraft:fly_one_cm":332468,"minecraft:open_barrel":11,"minecraft:open_chest":7,"minecraft:crouch_one_cm":2831,"minecraft:play_time":134963,"minecraft:deaths":3,"minecraft:sneak_time":2010,"minecraft:jump":991,"minecraft:leave_game":6,"minecraft:time_since_death":29403,"minecraft:walk_on_water_one_cm":17,"minecraft:climb_one_cm":600,"minecraft:total_world_time":134963,"cuffed:legcuffs_time_spent_restrained":13452,"minecraft:fall_one_cm":9138},"minecraft:killed_by":{"minecraft:player":2},"minecraft:picked_up":{"minecraft:clock":1,"minecraft:stone_button":2,"minecraft:cherry_fence":2,"minecraft:dirt":4,"minecraft:paper":14,"minecraft:bundle":2,"minecraft:arrow":5,"minecraft:pumpkin_pie":1,"minecraft:golden_hoe":1,"minecraft:crossbow":1,"minecraft:written_book":6,"minecraft:emerald":130,"minecraft:bread":81,"minecraft:chest":1},"minecraft:mined":{"minecraft:cherry_fence":2,"minecraft:dandelion":1,"minecraft:stone_button":1,"minecraft:grass_block":2,"minecraft:chest":1,"minecraft:dirt":2,"minecraft:oxeye_daisy":1},"minecraft:used":{"minecraft:bundle":1,"minecraft:bread":32,"minecraft:stone_button":1,"minecraft:chest":1,"minecraft:dirt":4,"minecraft:written_book":3,"minecraft:pumpkin_pie":1,"minecraft:cherry_fence":2},"minecraft:dropped":{"minecraft:bread":1,"minecraft:clock":1,"minecraft:stone_button":1,"minecraft:bundle":1,"minecraft:crossbow":1,"minecraft:golden_hoe":1,"minecraft:arrow":5,"minecraft:paper":2,"minecraft:written_book":3,"minecraft:emerald":122}},"DataVersion":3465}